chainerboard/__init__.py
chainerboard/_version.py
chainerboard/cli.py
chainerboard/exceptions.py
chainerboard/timeline.py
chainerboard/timeline_handler.py
chainerboard/util.py
chainerboard/watcher.py
chainerboard/app/__init__.py
chainerboard/app/events.py
chainerboard/app/histograms.py
chainerboard/app/root.py
chainerboard/app/static/css/bootstrap.min.css
chainerboard/app/static/css/font-awesome.min.css
chainerboard/app/static/css/main.css
chainerboard/app/static/css/tether.min.css
chainerboard/app/static/fonts/glyphicons-halflings-regular.woff
chainerboard/app/static/js/angular.min.js
chainerboard/app/static/js/bootstrap.min.js
chainerboard/app/static/js/common.js
chainerboard/app/static/js/events.js
chainerboard/app/static/js/histograms.js
chainerboard/app/static/js/jquery-2.1.4.min.js
chainerboard/app/static/js/plotly-1.28.3.min.js
chainerboard/app/static/js/tether.min.js
chainerboard/app/templates/layouts/base.html
chainerboard/app/templates/layouts/events.html
chainerboard/app/templates/layouts/histograms.html
chainerboard-0.1.3.dist-info/DESCRIPTION.rst
chainerboard-0.1.3.dist-info/METADATA
chainerboard-0.1.3.dist-info/RECORD
chainerboard-0.1.3.dist-info/WHEEL
chainerboard-0.1.3.dist-info/entry_points.txt
chainerboard-0.1.3.dist-info/metadata.json
chainerboard-0.1.3.dist-info/top_level.txt
