Metadata-Version: 2.0
Name: chainerboard
Version: 0.1.3
Summary: Visualization toolkit for Chainer
Home-page: https://github.com/koreyou/chainerboard
Author: Yuta Koreeda
Author-email: secret-email@example.com
License: MIT
Platform: UNKNOWN
Classifier: Environment :: Console
Classifier: Development Status :: 4 - Beta
Classifier: Intended Audience :: Developers
Classifier: Intended Audience :: Education
Classifier: Intended Audience :: Science/Research
Classifier: License :: OSI Approved :: MIT License
Classifier: Operating System :: OS Independent
Classifier: Programming Language :: Python :: 2.7
Classifier: Topic :: Scientific/Engineering :: Artificial Intelligence
Classifier: Topic :: Scientific/Engineering :: Information Analysis
Requires-Dist: Click
Requires-Dist: flask
Requires-Dist: numpy (>=1.10)
Requires-Dist: watchdog
